cosinnus_stream/__init__.py
cosinnus_stream/admin.py
cosinnus_stream/apps.py
cosinnus_stream/cosinnus_app.py
cosinnus_stream/dashboard.py
cosinnus_stream/forms.py
cosinnus_stream/mixins.py
cosinnus_stream/models.py
cosinnus_stream/urls.py
cosinnus_stream/views.py
cosinnus_stream/locale/de/LC_MESSAGES/django.mo
cosinnus_stream/locale/de/LC_MESSAGES/django.po
cosinnus_stream/locale/en/LC_MESSAGES/django.mo
cosinnus_stream/locale/en/LC_MESSAGES/django.po
cosinnus_stream/locale/fr/LC_MESSAGES/django.mo
cosinnus_stream/locale/fr/LC_MESSAGES/django.po
cosinnus_stream/locale/ru/LC_MESSAGES/django.mo
cosinnus_stream/locale/ru/LC_MESSAGES/django.po
cosinnus_stream/locale/uk/LC_MESSAGES/django.mo
cosinnus_stream/locale/uk/LC_MESSAGES/django.po
cosinnus_stream/migrations/0001_initial.py
cosinnus_stream/migrations/0002_auto_20151104_1711.py
cosinnus_stream/migrations/0003_auto_20160125_1339.py
cosinnus_stream/migrations/0004_auto_20160426_1345.py
cosinnus_stream/migrations/__init__.py
cosinnus_stream/static/css/cosinnus_stream.css
cosinnus_stream/templates/cosinnus_stream/base.html
cosinnus_stream/templates/cosinnus_stream/leftnav.html
cosinnus_stream/templates/cosinnus_stream/stream_detail.html
cosinnus_stream/templates/cosinnus_stream/stream_form.html
cosinnus_stream/templates/cosinnus_stream/widgets/my_streams.html
cosinnus_stream-0.5.dev20180515152708.data/data/cosinnus_stream/locale/de/LC_MESSAGES/django.mo
cosinnus_stream-0.5.dev20180515152708.data/data/cosinnus_stream/locale/de/LC_MESSAGES/django.po
cosinnus_stream-0.5.dev20180515152708.data/data/cosinnus_stream/locale/en/LC_MESSAGES/django.mo
cosinnus_stream-0.5.dev20180515152708.data/data/cosinnus_stream/locale/en/LC_MESSAGES/django.po
cosinnus_stream-0.5.dev20180515152708.data/data/cosinnus_stream/locale/fr/LC_MESSAGES/django.mo
cosinnus_stream-0.5.dev20180515152708.data/data/cosinnus_stream/locale/fr/LC_MESSAGES/django.po
cosinnus_stream-0.5.dev20180515152708.dist-info/DESCRIPTION.rst
cosinnus_stream-0.5.dev20180515152708.dist-info/METADATA
cosinnus_stream-0.5.dev20180515152708.dist-info/RECORD
cosinnus_stream-0.5.dev20180515152708.dist-info/WHEEL
cosinnus_stream-0.5.dev20180515152708.dist-info/metadata.json
cosinnus_stream-0.5.dev20180515152708.dist-info/top_level.txt
